eqr/__init__.py
eqr/epistemic_quantile_regressor.py
eqr/lightgbm_tuning.py
eqr/sklearn_gbr_tuning.py
eqr-0.1.17.dist-info/LICENSE
eqr-0.1.17.dist-info/METADATA
eqr-0.1.17.dist-info/WHEEL
eqr-0.1.17.dist-info/RECORD
